FixRaidenBoss2/__init__.py
FixRaidenBoss2/__main__.py
FixRaidenBoss2/main.py
FixRaidenBoss2/remapService.py
FixRaidenBoss2/constants/BufDataTypes.py
FixRaidenBoss2/constants/BufElementTypes.py
FixRaidenBoss2/constants/BufFormatNames.py
FixRaidenBoss2/constants/BufTypeNames.py
FixRaidenBoss2/constants/ByteSize.py
FixRaidenBoss2/constants/ColourConsts.py
FixRaidenBoss2/constants/Colours.py
FixRaidenBoss2/constants/DownloadMode.py
FixRaidenBoss2/constants/FileEncodings.py
FixRaidenBoss2/constants/FileExt.py
FixRaidenBoss2/constants/FilePathConsts.py
FixRaidenBoss2/constants/FilePrefixes.py
FixRaidenBoss2/constants/FileSuffixes.py
FixRaidenBoss2/constants/FileTypes.py
FixRaidenBoss2/constants/GIBuilder.py
FixRaidenBoss2/constants/GenericTypes.py
FixRaidenBoss2/constants/GlobalClassifiers.py
FixRaidenBoss2/constants/GlobalIniClassifiers.py
FixRaidenBoss2/constants/GlobalIniRemoveBuilders.py
FixRaidenBoss2/constants/GlobalPackageManager.py
FixRaidenBoss2/constants/IfPredPartType.py
FixRaidenBoss2/constants/ImgFormats.py
FixRaidenBoss2/constants/IniConsts.py
FixRaidenBoss2/constants/ModTypeBuilder.py
FixRaidenBoss2/constants/ModTypeNames.py
FixRaidenBoss2/constants/ModTypes.py
FixRaidenBoss2/constants/Packages.py
FixRaidenBoss2/constants/TexConsts.py
FixRaidenBoss2/constants/__init__.py
FixRaidenBoss2/controller/CommandBuilder.py
FixRaidenBoss2/controller/CommandFormatter.py
FixRaidenBoss2/controller/__init__.py
FixRaidenBoss2/controller/enums/CommandOpts.py
FixRaidenBoss2/controller/enums/ShortCommandOpts.py
FixRaidenBoss2/controller/enums/__init__.py
FixRaidenBoss2/data/FileDownloadData.py
FixRaidenBoss2/data/HashData.py
FixRaidenBoss2/data/IndexData.py
FixRaidenBoss2/data/IniFixBuilderData.py
FixRaidenBoss2/data/IniParseBuilderData.py
FixRaidenBoss2/data/ModData.py
FixRaidenBoss2/data/ModDataAssets.py
FixRaidenBoss2/data/PositionEditorData.py
FixRaidenBoss2/data/TexcoordByteSizeData.py
FixRaidenBoss2/data/VGRemapData.py
FixRaidenBoss2/data/VertexCountData.py
fixraidenboss2-4.6.2.dist-info/licenses/LICENSE
fixraidenboss2-4.6.2.dist-info/METADATA
fixraidenboss2-4.6.2.dist-info/WHEEL
fixraidenboss2-4.6.2.dist-info/top_level.txt
fixraidenboss2-4.6.2.dist-info/RECORD
